LICENSE
MANIFEST.in
README.md
setup.py
cloak/__init__.py
cloak/middleware.py
cloak/models.py
cloak/tests.py
cloak/urls.py
cloak/views.py
cloak/management/__init__.py
cloak/management/commands/__init__.py
cloak/management/commands/login.py
django_cloak.egg-info/PKG-INFO
django_cloak.egg-info/SOURCES.txt
django_cloak.egg-info/dependency_links.txt
django_cloak.egg-info/not-zip-safe
django_cloak.egg-info/requires.txt
django_cloak.egg-info/top_level.txt