Metadata-Version: 1.0
Name: django-cloak
Version: 1.0.0
Summary: App for Django to cloak as a user, or generate a login link
Home-page: https://github.com/PSU-OIT-ARC/django-cloak
Author: Matt Johnson
Author-email: mdj2@pdx.edu
License: UNKNOWN
Platform: UNKNOWN
Classifier: Framework :: Django
